spotify_terminal/.st
spotify_terminal/.version
spotify_terminal/__init__.py
spotify_terminal/api.py
spotify_terminal/authentication.py
spotify_terminal/cache.py
spotify_terminal/cache_reader.py
spotify_terminal/command.py
spotify_terminal/common.py
spotify_terminal/config.py
spotify_terminal/display.py
spotify_terminal/gui.py
spotify_terminal/main.py
spotify_terminal/model.py
spotify_terminal/periodic.py
spotify_terminal/state.py
spotify_terminal/unicurses.py
spotify_terminal/pdc34dll/curses.h
spotify_terminal/pdc34dll/panel.h
spotify_terminal/pdc34dll/pdcurses.dll
spotify_terminal/pdc34dll/pdcurses.lib
spotify_terminal-0.15.3.data/scripts/spotify-terminal.py
spotify_terminal-0.15.3.dist-info/LICENSE
spotify_terminal-0.15.3.dist-info/METADATA
spotify_terminal-0.15.3.dist-info/WHEEL
spotify_terminal-0.15.3.dist-info/top_level.txt
spotify_terminal-0.15.3.dist-info/RECORD
