Metadata-Version: 2.1
Name: spotify-terminal
Version: 0.15.3
Summary: Terminal Spotify application
Home-page: https://github.com/marcdjulien/spotify-terminal
Author: Marc-Daniel Julien
Author-email: marcdjulien@gmail.com
License: UNKNOWN
Platform: UNKNOWN
Classifier: Programming Language :: Python :: 3
Classifier: License :: OSI Approved :: GNU General Public License v3 or later (GPLv3+)
Classifier: Operating System :: OS Independent
Requires-Dist: requests
